rtl/cpu/regfile.sv
module regfile (
    input  logic        clk,
    input  logic        rst,

    input  logic [4:0]  rs1_addr,
    input  logic [4:0]  rs2_addr,

    output logic [31:0] rs1_data,
    output logic [31:0] rs2_data,

    input  logic        rd_we,
    input  logic [4:0]  rd_addr,
    input  logic [31:0] rd_data
);

    logic [31:0] regs [0:31];
    integer i;

    // Sequential Write Port
    always_ff @(posedge clk) begin
        if (rst) begin
            for (i = 0; i < 32; i = i + 1)
                regs[i] <= 32'b0;
        end
        else begin
            if (rd_we && (rd_addr != 5'd0)) begin
                regs[rd_addr] <= rd_data;
            end
        end
    end

    // Combinational Read Ports
    always_comb begin
        if (rs1_addr == 5'd0)
            rs1_data = 32'b0;
        else
            rs1_data = regs[rs1_addr];

        if (rs2_addr == 5'd0)
            rs2_data = 32'b0;
        else
            rs2_data = regs[rs2_addr];
    end

endmodule

tb/regfile_tb.sv
`timescale 1ns/1ps

module regfile_tb;

    logic clk;
    logic rst;

    logic [4:0] rs1_addr;
    logic [4:0] rs2_addr;

    logic [31:0] rs1_data;
    logic [31:0] rs2_data;

    logic        rd_we;
    logic [4:0]  rd_addr;
    logic [31:0] rd_data;

    regfile dut (
        .clk      (clk),
        .rst      (rst),

        .rs1_addr (rs1_addr),
        .rs2_addr (rs2_addr),

        .rs1_data (rs1_data),
        .rs2_data (rs2_data),

        .rd_we    (rd_we),
        .rd_addr  (rd_addr),
        .rd_data  (rd_data)
    );

    // Clock
    always #5 clk = ~clk;

    initial begin
     $dumpfile("regfile.vcd");
     $dumpvars(0, regfile_tb);   

        $display("=================================");
        $display(" Register File Test");
        $display("=================================");

        clk = 0;
        rst = 1;

        rs1_addr = 0;
        rs2_addr = 0;

        rd_we   = 0;
        rd_addr = 0;
        rd_data = 0;

        // Reset
        #12;
        rst = 0;

        // Test 1: Write x1
        @(negedge clk);

        rd_we   = 1;
        rd_addr = 5'd1;
        rd_data = 32'h12345678;

        @(negedge clk);

        rd_we = 0;

        // Read x1
        rs1_addr = 5'd1;

        #2;

        if (rs1_data == 32'h12345678)
            $display("PASS: x1 write/read");
        else
            $display("FAIL: x1 write/read");

        // Test 2: Write x2
        @(negedge clk);

        rd_we   = 1;
        rd_addr = 5'd2;
        rd_data = 32'hABCDEF01;

        @(negedge clk);

        rd_we = 0;

        rs2_addr = 5'd2;

        #2;

        if (rs2_data == 32'hABCDEF01)
            $display("PASS: x2 write/read");
        else
            $display("FAIL: x2 write/read");

        // Test 3: x0 must remain zero
        @(negedge clk);

        rd_we   = 1;
        rd_addr = 5'd0;
        rd_data = 32'hFFFFFFFF;

        @(negedge clk);

        rd_we = 0;

        rs1_addr = 5'd0;

        #2;

        if (rs1_data == 32'h00000000)
            $display("PASS: x0 remains zero");
        else
            $display("FAIL: x0 was modified");

        // Test 4: Two simultaneous reads
        rs1_addr = 5'd1;
        rs2_addr = 5'd2;

        #2;

        if ((rs1_data == 32'h12345678) &&
            (rs2_data == 32'hABCDEF01))
            $display("PASS: dual read ports");
        else
            $display("FAIL: dual read ports");

        $display("=================================");
        $display("Register File Test Completed");
        $display("=================================");

        $finish;

    end

endmodule

regfile.vcd
$date
	Fri Aug 28 10:55:41 2026
$end
$version
	Icarus Verilog
$end
$timescale
	1ps
$end
$scope module regfile_tb $end
$var wire 32 ! rs2_data [31:0] $end
$var wire 32 " rs1_data [31:0] $end
$var reg 1 # clk $end
$var reg 5 $ rd_addr [4:0] $end
$var reg 32 % rd_data [31:0] $end
$var reg 1 & rd_we $end
$var reg 5 ' rs1_addr [4:0] $end
$var reg 5 ( rs2_addr [4:0] $end
$var reg 1 ) rst $end
$scope module dut $end
$var wire 1 # clk $end
$var wire 5 * rd_addr [4:0] $end
$var wire 32 + rd_data [31:0] $end
$var wire 1 & rd_we $end
$var wire 5 , rs1_addr [4:0] $end
$var wire 5 - rs2_addr [4:0] $end
$var wire 1 ) rst $end
$var reg 32 . rs1_data [31:0] $end
$var reg 32 / rs2_data [31:0] $end
$var integer 32 0 i [31:0] $end
$upscope $end
$upscope $end
$enddefinitions $end
$comment Show the parameter values. $end
$dumpall
$end
#0
$dumpvars
bx 0
b0 /
b0 .
b0 -
b0 ,
b0 +
b0 *
1)
b0 (
b0 '
0&
b0 %
b0 $
0#
b0 "
b0 !
$end
#5000
b100000 0
1#
#10000
0#
#12000
0)
#15000
1#
#20000
b10010001101000101011001111000 %
b10010001101000101011001111000 +
b1 $
b1 *
1&
0#
#25000
1#
#30000
b10010001101000101011001111000 "
b10010001101000101011001111000 .
b1 '
b1 ,
0&
0#
#35000
1#
#40000
b10101011110011011110111100000001 %
b10101011110011011110111100000001 +
b10 $
b10 *
1&
0#
#45000
1#
#50000
b10101011110011011110111100000001 !
b10101011110011011110111100000001 /
b10 (
b10 -
0&
0#
#55000
1#
#60000
b11111111111111111111111111111111 %
b11111111111111111111111111111111 +
b0 $
b0 *
1&
0#
#65000
1#
#70000
b0 "
b0 .
b0 '
b0 ,
0&
0#
#72000
b10010001101000101011001111000 "
b10010001101000101011001111000 .
b1 '
b1 ,
