rtl/cpu/alu.sv
module alu (
    input  logic [31:0] a,
    input  logic [31:0] b,
    input  logic [3:0]  alu_op,

    output logic [31:0] result,
    output logic        zero
);

    // ALU operation codes
    localparam logic [3:0] ALU_ADD = 4'b0000;
    localparam logic [3:0] ALU_SUB = 4'b0001;
    localparam logic [3:0] ALU_AND = 4'b0010;
    localparam logic [3:0] ALU_OR  = 4'b0011;
    localparam logic [3:0] ALU_XOR = 4'b0100;
    localparam logic [3:0] ALU_SLT = 4'b0101;
    localparam logic [3:0] ALU_SLL = 4'b0110;
    localparam logic [3:0] ALU_SRL = 4'b0111;
    localparam logic [3:0] ALU_SRA = 4'b1000;

    always_comb begin

        // Default result
        result = 32'b0;

        case (alu_op)

            ALU_ADD: begin
                result = a + b;
            end

            ALU_SUB: begin
                result = a - b;
            end

            ALU_AND: begin
                result = a & b;
            end

            ALU_OR: begin
                result = a | b;
            end

            ALU_XOR: begin
                result = a ^ b;
            end

            ALU_SLT: begin
                result = ($signed(a) < $signed(b)) ? 32'd1 : 32'd0;
            end

            ALU_SLL: begin
                result = a << b[4:0];
            end

            ALU_SRL: begin
                result = a >> b[4:0];
            end

            ALU_SRA: begin
                result = $signed(a) >>> b[4:0];
            end

            default: begin
                result = 32'b0;
            end

        endcase
    end

    // Zero flag
    assign zero = (result == 32'b0);

endmodule

tb/unit/alu_tb.sv
`timescale 1ns/1ps

module alu_tb;

    logic [31:0] a;
    logic [31:0] b;
    logic [3:0]  alu_op;

    logic [31:0] result;
    logic        zero;

    integer errors;

    // ALU operation codes
    localparam logic [3:0] ALU_ADD = 4'b0000;
    localparam logic [3:0] ALU_SUB = 4'b0001;
    localparam logic [3:0] ALU_AND = 4'b0010;
    localparam logic [3:0] ALU_OR  = 4'b0011;
    localparam logic [3:0] ALU_XOR = 4'b0100;
    localparam logic [3:0] ALU_SLT = 4'b0101;
    localparam logic [3:0] ALU_SLL = 4'b0110;
    localparam logic [3:0] ALU_SRL = 4'b0111;
    localparam logic [3:0] ALU_SRA = 4'b1000;

    // Instantiate ALU
    alu dut (
        .a      (a),
        .b      (b),
        .alu_op (alu_op),
        .result (result),
        .zero   (zero)
    );

    // Self-checking task
    task automatic check_result(
        input logic [31:0] expected,
        input string       test_name
    );
        begin

            #1;

            if (result !== expected) begin
                $display("FAIL: %s", test_name);
                $display("      A        = %h", a);
                $display("      B        = %h", b);
                $display("      Expected = %h", expected);
                $display("      Actual   = %h", result);
                errors = errors + 1;
            end
            else begin
                $display("PASS: %s -> Result = %h",
                         test_name, result);
            end

            if (zero !== (expected == 32'b0)) begin
                $display("FAIL: Zero flag incorrect in %s", test_name);
                errors = errors + 1;
            end

        end
    endtask

    initial begin

        errors = 0;

        // Create waveform file
        $dumpfile("sim/alu.vcd");
        $dumpvars(0, alu_tb);

        $display("");
        $display("======================================");
        $display("       32-BIT ALU TESTBENCH");
        $display("======================================");
        $display("");

        // ------------------------------------------------
        // ADD
        // ------------------------------------------------
        a = 32'd10;
        b = 32'd5;
        alu_op = ALU_ADD;
        check_result(32'd15, "ADD 10 + 5");

        // ------------------------------------------------
        // SUB
        // ------------------------------------------------
        a = 32'd10;
        b = 32'd5;
        alu_op = ALU_SUB;
        check_result(32'd5, "SUB 10 - 5");

        // ------------------------------------------------
        // AND
        // ------------------------------------------------
        a = 32'hF0F0_F0F0;
        b = 32'h0F0F_0F0F;
        alu_op = ALU_AND;
        check_result(32'h0000_0000, "AND");

        // ------------------------------------------------
        // OR
        // ------------------------------------------------
        a = 32'hF0F0_0000;
        b = 32'h0000_0F0F;
        alu_op = ALU_OR;
        check_result(32'hF0F0_0F0F, "OR");

        // ------------------------------------------------
        // XOR
        // ------------------------------------------------
        a = 32'hFFFF_0000;
        b = 32'h0F0F_0F0F;
        alu_op = ALU_XOR;
        check_result(32'hF0F0_0F0F, "XOR");

        // ------------------------------------------------
        // SLT signed
        // ------------------------------------------------
        a = 32'hFFFF_FFFF;   // -1
        b = 32'd1;
        alu_op = ALU_SLT;
        check_result(32'd1, "SLT -1 < 1");

        // ------------------------------------------------
        // SLL
        // ------------------------------------------------
        a = 32'd1;
        b = 32'd4;
        alu_op = ALU_SLL;
        check_result(32'd16, "SLL 1 << 4");

        // ------------------------------------------------
        // SRL
        // ------------------------------------------------
        a = 32'd16;
        b = 32'd2;
        alu_op = ALU_SRL;
        check_result(32'd4, "SRL 16 >> 2");

        // ------------------------------------------------
        // SRA
        // ------------------------------------------------
        a = 32'hFFFF_FFF0;   // -16
        b = 32'd2;
        alu_op = ALU_SRA;
        check_result(32'hFFFF_FFFC, "SRA -16 >>> 2");

        // ------------------------------------------------
        // Zero result
        // ------------------------------------------------
        a = 32'd25;
        b = 32'd25;
        alu_op = ALU_SUB;
        check_result(32'd0, "SUB 25 - 25");

        // ------------------------------------------------
        // Final result
        // ------------------------------------------------
        $display("");
        $display("======================================");

        if (errors == 0) begin
            $display("       ALL TESTS PASSED");
        end
        else begin
            $display("       TESTS FAILED");
            $display("       ERROR COUNT = %0d", errors);
        end

        $display("======================================");
        $display("");

        $finish;
    end

endmodule

sim/alu.vcd
$date
	Fri Aug 28 09:54:57 2026
$end
$version
	Icarus Verilog
$end
$timescale
	1ps
$end
$scope module alu_tb $end
$var wire 1 ! zero $end
$var wire 32 " result [31:0] $end
$var parameter 4 # ALU_ADD $end
$var parameter 4 $ ALU_AND $end
$var parameter 4 % ALU_OR $end
$var parameter 4 & ALU_SLL $end
$var parameter 4 ' ALU_SLT $end
$var parameter 4 ( ALU_SRA $end
$var parameter 4 ) ALU_SRL $end
$var parameter 4 * ALU_SUB $end
$var parameter 4 + ALU_XOR $end
$var reg 32 , a [31:0] $end
$var reg 4 - alu_op [3:0] $end
$var reg 32 . b [31:0] $end
$var integer 32 / errors [31:0] $end
$scope module dut $end
$var wire 32 0 a [31:0] $end
$var wire 4 1 alu_op [3:0] $end
$var wire 32 2 b [31:0] $end
$var wire 1 ! zero $end
$var parameter 4 3 ALU_ADD $end
$var parameter 4 4 ALU_AND $end
$var parameter 4 5 ALU_OR $end
$var parameter 4 6 ALU_SLL $end
$var parameter 4 7 ALU_SLT $end
$var parameter 4 8 ALU_SRA $end
$var parameter 4 9 ALU_SRL $end
$var parameter 4 : ALU_SUB $end
$var parameter 4 ; ALU_XOR $end
$var reg 32 < result [31:0] $end
$upscope $end
$scope task check_result $end
$upscope $end
$upscope $end
$enddefinitions $end
$comment Show the parameter values. $end
$dumpall
b100 ;
b1 :
b111 9
b1000 8
b101 7
b110 6
b11 5
b10 4
b0 3
b100 +
b1 *
b111 )
b1000 (
b101 '
b110 &
b11 %
b10 $
b0 #
$end
#0
$dumpvars
b1111 <
b101 2
b0 1
b1010 0
b0 /
b101 .
b0 -
b1010 ,
b1111 "
0!
$end
#1000
0!
b101 "
b101 <
b1 -
b1 1
#2000
1!
b0 "
b0 <
b10 -
b10 1
b1111000011110000111100001111 .
b1111000011110000111100001111 2
b11110000111100001111000011110000 ,
b11110000111100001111000011110000 0
#3000
0!
b11110000111100000000111100001111 "
b11110000111100000000111100001111 <
b11 -
b11 1
b111100001111 .
b111100001111 2
b11110000111100000000000000000000 ,
b11110000111100000000000000000000 0
#4000
0!
b11110000111100000000111100001111 "
b11110000111100000000111100001111 <
b100 -
b100 1
b1111000011110000111100001111 .
b1111000011110000111100001111 2
b11111111111111110000000000000000 ,
b11111111111111110000000000000000 0
#5000
0!
b1 "
b1 <
b101 -
b101 1
b1 .
b1 2
b11111111111111111111111111111111 ,
b11111111111111111111111111111111 0
#6000
0!
b10000 "
b10000 <
b110 -
b110 1
b100 .
b100 2
b1 ,
b1 0
#7000
0!
b100 "
b100 <
b111 -
b111 1
b10 .
b10 2
b10000 ,
b10000 0
#8000
0!
b11111111111111111111111111111100 "
b11111111111111111111111111111100 <
b1000 -
b1000 1
b11111111111111111111111111110000 ,
b11111111111111111111111111110000 0
#9000
1!
b0 "
b0 <
b1 -
b1 1
b11001 .
b11001 2
b11001 ,
b11001 0
